setup.py
distributions/Binomialdistribution.py
distributions/Gaussiandistribution.py
distributions/Generaldistribution.py
distributions/__init__.py
distributionsfeena.egg-info/PKG-INFO
distributionsfeena.egg-info/SOURCES.txt
distributionsfeena.egg-info/dependency_links.txt
distributionsfeena.egg-info/not-zip-safe
distributionsfeena.egg-info/top_level.txt