Metadata-Version: 1.0
Name: distributionsfeena
Version: 0.2
Summary: Gaussian distributions
Home-page: UNKNOWN
Author:  Rafeena 
Author-email: UNKNOWN
License: UNKNOWN
Platform: UNKNOWN
